secure_js_login/__init__.py
secure_js_login/settings.py
secure_js_login/auth_backends.py
secure_js_login/urls.py
secure_js_login/admin.py
secure_js_login/models.py
secure_js_login/views.py
secure_js_login/forms.py
secure_js_login/utils/base_models.py
secure_js_login/utils/__init__.py
secure_js_login/utils/crypt.py
secure_js_login/honypot/__init__.py
secure_js_login/honypot/urls.py
secure_js_login/honypot/admin.py
secure_js_login/honypot/models.py
secure_js_login/honypot/views.py
secure_js_login/honypot/forms.py
secure_js_login/templates/secure_js_login/login_info.html
secure_js_login/templates/secure_js_login/profile_index.html
secure_js_login/templates/secure_js_login/JS_password_change.html
secure_js_login/templates/secure_js_login/logout_link.html
secure_js_login/templates/secure_js_login/login_link.html
secure_js_login/templates/secure_js_login/django_login.html
secure_js_login/templates/secure_js_login/login_link_https.html
secure_js_login/templates/secure_js_login/secure_js_login.html
secure_js_login/static/secure_js_login/sha.js
secure_js_login/static/secure_js_login/pbkdf2.js
secure_js_login/static/secure_js_login/secure_js_login.js
example_project/manage.py
example_project/__init__.py
example_project/example_project/__init__.py
example_project/example_project/settings.py
example_project/example_project/wsgi.py
example_project/example_project/urls.py
example_project/example_project/views.py
example_project/example_project/templates/example_project/index.html
django_secure_js_login-0.2.0.dist-info/top_level.txt
django_secure_js_login-0.2.0.dist-info/metadata.json
django_secure_js_login-0.2.0.dist-info/WHEEL
django_secure_js_login-0.2.0.dist-info/METADATA
django_secure_js_login-0.2.0.dist-info/LICENSE.txt
django_secure_js_login-0.2.0.dist-info/RECORD
django_secure_js_login-0.2.0.dist-info/DESCRIPTION.rst
tests/__init__.py
tests/test_live_server.py
tests/test_secure_login.py
tests/test_honeypot.py
tests/test_user_profile.py
tests/test_crypt.py
tests/test_utils/test_settings.py
tests/test_utils/__init__.py
tests/test_utils/test_cases.py
tests/test_utils/manipulators.py
