Metadata-Version: 2.0
Name: django-secure-js-login
Version: 0.2.0
Summary: JavaScript Challenge-handshake authentication django app
Home-page: https://github.com/jedie/django-secure-js-login
Author: Jens Diemer
Author-email: UNKNOWN
License: UNKNOWN
Platform: UNKNOWN
Classifier: Development Status :: 4 - Beta
Classifier: Environment :: Web Environment
Classifier: Intended Audience :: Developers
Classifier: License :: OSI Approved :: GNU General Public License (GPL)
Classifier: Programming Language :: Python
Classifier: Programming Language :: JavaScript
Classifier: Framework :: Django
Classifier: Topic :: Database :: Front-Ends
Classifier: Topic :: Documentation
Classifier: Topic :: Internet :: WWW/HTTP :: Dynamic Content
Classifier: Topic :: Internet :: WWW/HTTP :: Site Management
Classifier: Topic :: Internet :: WWW/HTTP :: WSGI :: Application
Classifier: Operating System :: OS Independent
Requires-Dist: Django (>=1.7,<1.9)
